injectslib/__init__.py
injectslib/api.py
injectslib/example.py
injectslib-0.0.1.dist-info/METADATA
injectslib-0.0.1.dist-info/WHEEL
injectslib-0.0.1.dist-info/top_level.txt
injectslib-0.0.1.dist-info/RECORD
