Metadata-Version: 2.1
Name: injectslib
Version: 0.0.1
Summary: Official API package for https://injects.cert.pl
Home-page: UNKNOWN
Author: msm
Author-email: msm@cert.pl
License: UNKNOWN
Platform: UNKNOWN
Classifier: Programming Language :: Python
Classifier: License :: OSI Approved :: MIT License
Classifier: Operating System :: OS Independent
Requires-Dist: requests
